SigTool.py
setup.py
cmapBQ/__init__.py
cmapBQ/__main__.py
cmapBQ/_version.py
cmapBQ/auth.py
cmapBQ/cli.py
cmapBQ/cmap_compounds.py
cmapBQ/config.py
cmapBQ/query.py
cmapBQ/utils.py
cmapBQ/archive/__init__.py
cmapBQ/archive/find_fail_cid.py
cmapBQ/archive/make_m2_summary.py
cmapBQ/tests/__init__.py
cmapBQ/tests/test_query.py
cmapBQ/tools/__init__.py
cmapBQ/tools/cmap_compounds.py
cmapBQ/tools/cmap_matrix.py
cmapBQ/tools/csv2gct.py
cmapBQ/tools/diff_tables.py
cmapBQ/tools/gctx2parquet.py
cmapBQ/tools/queryBQ.py
cmapBQ/tools/upload_parquet.py
cmapBQ/tools/upsert_table.py
cmapBQ/tools/validate_bq_table.py
cmapBQ/utils/__init__.py
cmapBQ/utils/file.py
cmapBQ-1.2.3.dist-info/LICENSE
cmapBQ-1.2.3.dist-info/METADATA
cmapBQ-1.2.3.dist-info/WHEEL
cmapBQ-1.2.3.dist-info/entry_points.txt
cmapBQ-1.2.3.dist-info/top_level.txt
cmapBQ-1.2.3.dist-info/RECORD
