Metadata-Version: 2.1
Name: cmapBQ
Version: 1.2.3
Summary: Toolkit for interacting with Google BigQuery and CMAP datasets
Home-page: https://github.com/cmap/cmapBQ
Author: Anup Jonchhe
Author-email: anup@broadinstitute.org
License: UNKNOWN
Project-URL: Documentation, https://cmapBQ.readthedocs.io/
Project-URL: Issue Tracker, https://github.com/cmap/cmapBQ/issues/
Platform: UNKNOWN
Classifier: Operating System :: Unix
Classifier: Operating System :: POSIX
Classifier: Operating System :: Microsoft :: Windows
Classifier: Programming Language :: Python
Classifier: Programming Language :: Python :: 3.6
Classifier: Programming Language :: Python :: 3.7
Classifier: Programming Language :: Python :: 3.8
Classifier: Programming Language :: Python :: Implementation :: PyPy
Requires-Dist: cmapPy
Requires-Dist: pandas
Requires-Dist: google-cloud-bigquery
Requires-Dist: google-cloud-bigquery-storage
Requires-Dist: google-cloud-storage
Requires-Dist: pandas-gbq
Requires-Dist: pyyaml
Requires-Dist: dacite
Requires-Dist: pyarrow
